mitre_stix/__init__.py
mitre_stix/scan_rules.py
mitre_stix/rules/T1002.py
mitre_stix/rules/T1003.py
mitre_stix/rules/T1007.py
mitre_stix/rules/T1012.py
mitre_stix/rules/T1013.py
mitre_stix/rules/T1016.py
mitre_stix/rules/T1018.py
mitre_stix/rules/T1021.py
mitre_stix/rules/T1027.py
mitre_stix/rules/T1028.py
mitre_stix/rules/T1031.py
mitre_stix/rules/T1033.py
mitre_stix/rules/T1035.py
mitre_stix/rules/T1043.py
mitre_stix/rules/T1046.py
mitre_stix/rules/T1047.py
mitre_stix/rules/T1048.py
mitre_stix/rules/T1049.py
mitre_stix/rules/T1050.py
mitre_stix/rules/T1053e.py
mitre_stix/rules/T1053p.py
mitre_stix/rules/T1054.py
mitre_stix/rules/T1057.py
mitre_stix/rules/T1059.py
mitre_stix/rules/T1063.py
mitre_stix/rules/T1064de.py
mitre_stix/rules/T1064e.py
mitre_stix/rules/T1069.py
mitre_stix/rules/T1070.py
mitre_stix/rules/T1076.py
mitre_stix/rules/T1077.py
mitre_stix/rules/T1081.py
mitre_stix/rules/T1082.py
mitre_stix/rules/T1083.py
mitre_stix/rules/T1084.py
mitre_stix/rules/T1085de.py
mitre_stix/rules/T1085e.py
mitre_stix/rules/T1086.py
mitre_stix/rules/T1087.py
mitre_stix/rules/T1089.py
mitre_stix/rules/T1090cnc.py
mitre_stix/rules/T1090de.py
mitre_stix/rules/T1094.py
mitre_stix/rules/T1096.py
mitre_stix/rules/T1098ca.py
mitre_stix/rules/T1098p.py
mitre_stix/rules/T1100.py
mitre_stix/rules/T1102cnc.py
mitre_stix/rules/T1102de.py
mitre_stix/rules/T1105cnc.py
mitre_stix/rules/T1105lm.py
mitre_stix/rules/T1107.py
mitre_stix/rules/T1108de.py
mitre_stix/rules/T1108p.py
mitre_stix/rules/T1110.py
mitre_stix/rules/T1117 de.py
mitre_stix/rules/T1117e.py
mitre_stix/rules/T1118de.py
mitre_stix/rules/T1118e.py
mitre_stix/rules/T1119.py
mitre_stix/rules/T1121de.py
mitre_stix/rules/T1121e.py
mitre_stix/rules/T1124.py
mitre_stix/rules/T1126.py
mitre_stix/rules/T1128.py
mitre_stix/rules/T1130.py
mitre_stix/rules/T1134de.py
mitre_stix/rules/T1134pe.py
mitre_stix/rules/T1135.py
mitre_stix/rules/T1136.py
mitre_stix/rules/T1138.py
mitre_stix/rules/T1140.py
mitre_stix/rules/T1143.py
mitre_stix-0.0.7.dist-info/LICENSE
mitre_stix-0.0.7.dist-info/METADATA
mitre_stix-0.0.7.dist-info/WHEEL
mitre_stix-0.0.7.dist-info/top_level.txt
mitre_stix-0.0.7.dist-info/RECORD
