Metadata-Version: 2.1
Name: mitre-stix
Version: 0.0.7
Summary: A Python package that scans mitre signatures from STIX2.0 json log format
Home-page: https://github.trendmicro.com/henryal/mitre-stix
Author: Henry Alarcon Jr.
Author-email: henry_alarconjr@trendmicro.com
License: MIT
Keywords: Cyber threat intelligence
Platform: UNKNOWN
Classifier: Development Status :: 4 - Beta
Classifier: Operating System :: OS Independent
Classifier: Topic :: Security
Classifier: License :: OSI Approved :: MIT License
Requires-Python: >=3.0
